src/fifo.v
`timescale 1ns/1ps
// There are several situations that can be met
// External signals:
// 1. wre=0, rde=0
// 2. wre=1, rde=0
// 3. wre=0, rde=1
// 4. wre=1, rde=1
//
// Internal states:
// a. f=0, e=1
// b. f=0, e=0
// c. f=1, e=0
// !. f=1, e=1 fatal error, this state can't be reached

module fifo (input wire reset,
             
             input wire clk_w,
             input wire wre,
             input wire [7:0] wrd,
             
//              input wire clk_r,
             input wire rde,
             
             output reg [7:0] rdd,
             
             output reg full,
             output reg empty
            );
  
  reg [7:0] data[2:0];	// Array of registers
  reg [2:0] wri; 		// Index of register to write data in
  
  always @(posedge clk_w, posedge reset) begin
    if (reset == 1) begin
      data[0] <= 0;
      empty <= 1;
      full <= 0;
      rdd <= 0;
      wri <= 2;
    end
    
    case ({wre, rde})
      2'b10: /* 2. wre=1, rde=0 */ begin
        if (full == 0) begin
          data[wri] <= wrd;
          
          if (empty == 1)
            empty <= 0;
          
          if (wri == 0)
            full <= 1;
          else
          	wri <= wri - 1;
        end
      end
      
      2'b01: /* 3. wre=0, rde=1 */ begin
        if (empty == 0) begin
          rdd <= data[2];
          data[2] <= data[1];
          data[1] <= data[0];
          
          if (full == 1)
            full <= 0;
          else 
            wri <= wri + 1;
          
          if (wri == 1)
            empty <= 1;
        end
        
      end
      
      2'b11: /* 4. wre=1, rde=1 */ begin
        if (full == 0 & empty == 1) begin
          data[wri] <= wrd;
          empty <= 0;
          wri <= wri - 1;
        end
        
        if (full == 0 & empty == 0) begin
          
          data[wri + 1] <= wrd;
          
          rdd <= data[2];
          data[2] <= data[1];
          data[1] <= data[0];

        end
        
        if (full == 1 & empty == 0) begin
          data[wri] <= wrd;
          
          rdd <= data[2];
          data[2] <= data[1];
          data[1] <= data[0];
          
        end
        
      end
     
      default: /* 1. wre=0, rde=0 */ begin
      end
    endcase

  end
  
  
endmodule

src/fifo_tb.v
`timescale 1ns/1ps

module tb_fifo;

  reg reset;
  reg clk_w;
  reg wre;
  reg [7:0] wrd;
//   reg clk_r;
  reg rde;
  wire [7:0] rdd;
  wire full;
  wire empty;
  
  fifo fifo1(.reset(reset),
             
             .clk_w(clk_w), 
             .wre(wre),
             .wrd(wrd),
             
//              .clk_r(clk_r),
             .rde(rde),
             
             .rdd(rdd),
             
             .full(full),
             .empty(empty)
            );
  
  initial begin
  	reset = 0;
    clk_w = 0;
    wre = 0;
    rde = 0;
    #3 reset = 1;
    #3 reset = 0;
    
    wrd = 8'hA5;
    #4 wre = 1;
    #6 wre = 0;
    
    #5 wrd = 8'h5A;
    #4 wre = 1;
    #6 wre = 0;
    
    #5 wrd = 8'hFF;
    #4 wre = 1;
    #6 wre = 0;
    
    #5 wrd = 8'h00;
    #4 wre = 1;
    #6 wre = 0;
    
    $monitor($time, ,clk_w, ,reset, ,wre, ,wrd);
  end
  
  initial begin
    $dumpfile("dump.vcd");
    $dumpvars(0, fifo1);
  end
  
    initial
    #100 $finish;
  
  always
    #5 clk_w = ~clk_w;
  
endmodule

icarus/fifo_sim/dump.vcd
$date
	Thu Jun  2 13:45:49 2022
$end
$version
	Icarus Verilog
$end
$timescale
	1ps
$end
$scope module tb_fifo $end
$scope module fifo1 $end
$var wire 1 ! clk_w $end
$var wire 1 " rde $end
$var wire 1 # reset $end
$var wire 8 $ wrd [7:0] $end
$var wire 1 % wre $end
$var reg 1 & empty $end
$var reg 1 ' full $end
$var reg 8 ( rdd [7:0] $end
$var reg 3 ) wri [2:0] $end
$upscope $end
$upscope $end
$enddefinitions $end
#0
$dumpvars
bx )
bx (
x'
x&
0%
bx $
0#
0"
0!
$end
#3000
b10 )
b0 (
0'
1&
1#
#5000
1!
#6000
b10100101 $
0#
#10000
1%
0!
#15000
b1 )
0&
1!
#16000
0%
#20000
0!
#21000
b1011010 $
#25000
b0 )
1%
1!
#30000
0!
#31000
0%
#35000
1!
#36000
b11111111 $
#40000
1%
0!
#45000
1'
1!
#46000
0%
#50000
0!
#51000
b0 $
#55000
1%
1!
#60000
0!
#61000
0%
